LICENSE
LICENSE.conformalmappingtoolbox
MANIFEST.in
README.rst
setup.py
cmtoolkit.egg-info/PKG-INFO
cmtoolkit.egg-info/SOURCES.txt
cmtoolkit.egg-info/dependency_links.txt
cmtoolkit.egg-info/top_level.txt
conformalmapping/__init__.py
conformalmapping/circle.py
conformalmapping/closedcurve.py
conformalmapping/conformalmap.py
conformalmapping/disk.py
conformalmapping/gridcurves.py
conformalmapping/homog.py
conformalmapping/mobius.py
conformalmapping/mobiusbase.py
conformalmapping/region.py
conformalmapping/unitdisk.py
conformalmapping/zline.py
conformalmapping/cmt/__init__.py