Metadata-Version: 1.1
Name: cmtoolkit
Version: 0.0.1
Summary: Conformal Mapping Toolkit (ported to Python)
Home-page: http://github.com/AndrewWalker/cmtoolkit
Author: Andrew Walker
Author-email: walker.ab@gmail.com
License: BSD
Platform: UNKNOWN
Classifier: Development Status :: 1 - Planning
Classifier: Intended Audience :: Science/Research
Classifier: License :: OSI Approved :: MIT License
Classifier: Topic :: Scientific/Engineering :: Mathematics
Classifier: Programming Language :: Python :: 2
Classifier: Programming Language :: Python :: 2.7
Classifier: Programming Language :: Python :: 3
Classifier: Programming Language :: Python :: 3.4
